{"train": {"experiment_id": "2024-05-08-caformer_s18-focal-balanced-sampling-paused", "model_id": "caformer_s18.sail_in22k_ft_in1k_384", "epochs": 200, "lr": 0.001, "lr_after_unfreeze": 5e-05, "pretrained": true, "early_stop_thresh": 10, "loss_function": "focal", "worker_timeout_s": 360, "image_resize": 384, "max_norm": 1.0, "dropout_rate": 0.2, "weight_decay": 0.05, "balanced_sampler": true, "fine_tune_after_n_epochs": 5, "n_classes": 1784, "lr_scheduler": "reducelronplateau", "lr_scheduler_patience": 4, "train_progressively": false, "use_venom_loss": true, "use_logitnorm": true, "use_class_weights_venom_loss": false, "use_lr_finder": false, "notes": "trivial aug, double resize before randomcrop", "batch_size": 40, "num_dataloader_workers": 16}, "train_aug": {"trivial_aug": true, "auto_aug": false, "random_aug": false, "gridmask_prob": null}, "progressive-learning": {"start_image_size": 384, "end_image_size": 384, "start_dropout": 0.1, "end_dropout": 0.3, "start_batch_size": 32, "end_batch_size": 32, "progression_epochs": 100}, "evaluate": {"experiment_id": "2024-05-08-caformer_s18-focal-balanced-sampling-paused", "model_id": "caformer_s18.sail_in22k_ft_in1k_384", "image_size": 768}}